eclipse/__init__.py
eclipse/eclipse.py
eclipse_ai-1.0.0b4.dist-info/LICENSE.md
eclipse_ai-1.0.0b4.dist-info/METADATA
eclipse_ai-1.0.0b4.dist-info/WHEEL
eclipse_ai-1.0.0b4.dist-info/entry_points.txt
eclipse_ai-1.0.0b4.dist-info/top_level.txt
eclipse_ai-1.0.0b4.dist-info/RECORD
