Metadata-Version: 2.1
Name: eclipse-ai
Version: 1.0.0b4
Summary: AI Powered Sensitive Information Detector
Home-page: https://github.com/berylliumsec/eclipse
Author: David I
Author-email: david@berylliumsec.com
License: BSD
Keywords: AI,PII,Machine Learning,Sensitive Information Detection,Privacy
Classifier: Development Status :: 4 - Beta
Classifier: Intended Audience :: Developers
Classifier: License :: OSI Approved :: BSD License
Classifier: Operating System :: OS Independent
Classifier: Programming Language :: Python :: 3
Classifier: Topic :: Software Development :: Libraries :: Python Modules
Classifier: Topic :: Security
Classifier: Topic :: Text Processing :: Linguistic
Requires-Python: >=3.10
License-File: LICENSE.md
Requires-Dist: torch >=1.0.1
Requires-Dist: transformers >=4.34.0
Requires-Dist: requests
Requires-Dist: termcolor
Requires-Dist: prompt-toolkit
